numbagg/__init__.py
numbagg/decorators.py
numbagg/funcs.py
numbagg/funcs.pyi
numbagg/grouped.py
numbagg/moving.py
numbagg/moving.pyi
numbagg/moving_exp.py
numbagg/moving_exp.pyi
numbagg/moving_matrix.py
numbagg/py.typed
numbagg/transform.py
numbagg/utils.py
numbagg/test/__init__.py
numbagg/test/conftest.py
numbagg/test/run_benchmarks.py
numbagg/test/test_axis_ordering_benchmark.py
numbagg/test/test_benchmark.py
numbagg/test/test_cache_segfault.py
numbagg/test/test_funcs.py
numbagg/test/test_grouped.py
numbagg/test/test_matrix_functions.py
numbagg/test/test_moving.py
numbagg/test/test_moving_exp.py
numbagg/test/test_multithreading.py
numbagg/test/test_property.py
numbagg/test/test_threading_detection.py
numbagg/test/test_utils.py
numbagg/test/util.py
numbagg-0.9.4.dist-info/licenses/LICENSE
numbagg-0.9.4.dist-info/METADATA
numbagg-0.9.4.dist-info/WHEEL
numbagg-0.9.4.dist-info/top_level.txt
numbagg-0.9.4.dist-info/RECORD
