Metadata-Version: 2.4
Name: numbagg
Version: 0.9.4
Summary: Fast N-dimensional aggregation functions with Numba
Author-email: Stephan Hoyer <shoyer@gmail.com>, Maximilian Roos <m@maxroos.com>
License: License
Project-URL: homepage, https://github.com/numbagg/numbagg
Classifier: Operating System :: OS Independent
Classifier: Intended Audience :: Science/Research
Classifier: Programming Language :: Python
Classifier: Programming Language :: Python :: 3
Classifier: Programming Language :: Python :: 3.10
Classifier: Programming Language :: Python :: 3.11
Classifier: Programming Language :: Python :: 3.12
Classifier: Programming Language :: Python :: 3.13
Classifier: Programming Language :: Python :: 3 :: Only
Classifier: Topic :: Scientific/Engineering
Requires-Python: >=3.10
License-File: LICENSE
Requires-Dist: numpy
Requires-Dist: numba
Dynamic: license-file
